{
  "category": "",
  "id": "35",
  "name": "Search Insert Position",
  "difficulty": "Easy",
  "leetcode_url": "https://leetcode.com/problems/search-insert-position/",
  "slug": "search-insert-position",
  "isPaidOnly": false,
  "tags": [
    "Array",
    "Binary Search"
  ],
  "similar_questions": [
    {
      "title": "First Bad Version",
      "difficulty": "Easy",
      "slug": "first-bad-version"
    },
    {
      "title": "Minimum Operations to Exceed Threshold Value I",
      "difficulty": "Easy",
      "slug": "minimum-operations-to-exceed-threshold-value-i"
    }
  ],
  "questionId": "35",
  "questionFrontendId": "35",
  "title": "Search Insert Position",
  "titleSlug": "search-insert-position",
  "content": "<p>Given a sorted array of distinct integers and a target value, return the index if the target is found. If not, return the index where it would be if it were inserted in order.</p>\n\n<p>You must&nbsp;write an algorithm with&nbsp;<code>O(log n)</code> runtime complexity.</p>\n\n<p>&nbsp;</p>\n<p><strong class=\"example\">Example 1:</strong></p>\n\n<pre>\n<strong>Input:</strong> nums = [1,3,5,6], target = 5\n<strong>Output:</strong> 2\n</pre>\n\n<p><strong class=\"example\">Example 2:</strong></p>\n\n<pre>\n<strong>Input:</strong> nums = [1,3,5,6], target = 2\n<strong>Output:</strong> 1\n</pre>\n\n<p><strong class=\"example\">Example 3:</strong></p>\n\n<pre>\n<strong>Input:</strong> nums = [1,3,5,6], target = 7\n<strong>Output:</strong> 4\n</pre>\n\n<p>&nbsp;</p>\n<p><strong>Constraints:</strong></p>\n\n<ul>\n\t<li><code>1 &lt;= nums.length &lt;= 10<sup>4</sup></code></li>\n\t<li><code>-10<sup>4</sup> &lt;= nums[i] &lt;= 10<sup>4</sup></code></li>\n\t<li><code>nums</code> contains <strong>distinct</strong> values sorted in <strong>ascending</strong> order.</li>\n\t<li><code>-10<sup>4</sup> &lt;= target &lt;= 10<sup>4</sup></code></li>\n</ul>\n",
  "likes": 17917,
  "dislikes": 851,
  "stats": {
    "totalAccepted": "4.1M",
    "totalSubmission": "8.3M",
    "totalAcceptedRaw": 4099940,
    "totalSubmissionRaw": 8263912,
    "acRate": "49.6%"
  },
  "topicTags": [
    {
      "name": "Array",
      "slug": "array"
    },
    {
      "name": "Binary Search",
      "slug": "binary-search"
    }
  ],
  "metaData": {
    "name": "searchInsert",
    "params": [
      {
        "name": "nums",
        "type": "integer[]"
      },
      {
        "name": "target",
        "type": "integer"
      }
    ],
    "return": {
      "type": "integer"
    }
  },
  "company_tag_stats": {
    "1": [
      {
        "taggedByAdmin": false,
        "name": "Amazon",
        "slug": "amazon",
        "timesEncountered": 11
      }
    ]
  },
  "discussion_posts": [
    {
      "name": "shoshinsha_coder",
      "year": 2022,
      "content": "I finally got a leetcode easy all by myself!! Even though this is an easy one it was so satisfying to pass all tests and edge cases. I just used a for loop with a bunch of if / if else statements. (Javascript)",
      "voteCount": 340
    },
    {
      "name": "columbianboi29",
      "year": 2023,
      "content": "I DID IT!!!!! I solved my first leet code problem \\uD83D\\uDE2D\\uD83D\\uDE2D\\uD83D\\uDE2D \\n",
      "voteCount": 276
    },
    {
      "name": "Celestial__Coder",
      "year": 2023,
      "content": "Seems like silence before the Storm.",
      "voteCount": 135
    },
    {
      "name": "Movsar",
      "year": 2023,
      "content": "The same as `binary search` but here `return leftPointer` at the end. \n\n**Time complexity:** *O(logn)*\n**Space complexity:** *O1*",
      "voteCount": 82
    },
    {
      "name": "AlgoEngine",
      "year": 2023,
      "content": "Video visualizing the binary search solution with an explanation of the O(log n) runtime:\nhttps://youtu.be/v4J_AWp-6EQ",
      "voteCount": 76
    },
    {
      "name": "nzjony",
      "year": 2021,
      "content": "I get the following issue with the testcase.\\n\\n[1]\\n1\\n\\nI output 1, but the expected is 0, why is that? Either 0 or 1 should be valid? Is there something I miss?",
      "voteCount": 43
    },
    {
      "name": "chetan_coding",
      "year": 2023,
      "content": "As a newbie at leetcode problem solving, I solved my first problem today in easy and fast way without Any difficulty and error.",
      "voteCount": 42
    },
    {
      "name": "shell769324",
      "year": 2018,
      "content": "It doesn\\'t make sense",
      "voteCount": 33
    },
    {
      "name": "scor32k",
      "year": 2023,
      "content": "leetcode leetcode leetcode leetcode leetcode leetcode leetforces leetcode :)\n\nthose who knwo they know",
      "voteCount": 21
    },
    {
      "name": "tejas_bhat_13",
      "year": 2024,
      "content": "i am not understanding how to return the index if the target is not present in the array  ",
      "voteCount": 13
    }
  ]
}
