{
  "category": "",
  "id": "645",
  "name": "Set Mismatch",
  "difficulty": "Easy",
  "leetcode_url": "https://leetcode.com/problems/set-mismatch/",
  "slug": "set-mismatch",
  "isPaidOnly": false,
  "tags": [
    "Array",
    "Hash Table",
    "Bit Manipulation",
    "Sorting"
  ],
  "similar_questions": [
    {
      "title": "Find the Duplicate Number",
      "slug": "find-the-duplicate-number",
      "id": null,
      "leetcode_url": "https://leetcode.com/problems/find-the-duplicate-number/"
    }
  ]
}
