{
  "category": "",
  "id": "1354",
  "name": "Construct Target Array With Multiple Sums",
  "difficulty": "Hard",
  "leetcode_url": "https://leetcode.com/problems/construct-target-array-with-multiple-sums/",
  "slug": "construct-target-array-with-multiple-sums",
  "isPaidOnly": false,
  "tags": [
    "Array",
    "Heap (Priority Queue)"
  ],
  "similar_questions": [
    {
      "title": "Minimum Amount of Time to Fill Cups",
      "slug": "minimum-amount-of-time-to-fill-cups",
      "id": null,
      "leetcode_url": "https://leetcode.com/problems/minimum-amount-of-time-to-fill-cups/"
    }
  ]
}