{
  "category": "",
  "id": "1606",
  "name": "Find Servers That Handled Most Number of Requests",
  "difficulty": "Hard",
  "leetcode_url": "https://leetcode.com/problems/find-servers-that-handled-most-number-of-requests/",
  "slug": "find-servers-that-handled-most-number-of-requests",
  "isPaidOnly": false,
  "tags": [
    "Array",
    "Greedy",
    "Heap (Priority Queue)",
    "Ordered Set"
  ],
  "similar_questions": [
    {
      "title": "Meeting Rooms III",
      "slug": "meeting-rooms-iii",
      "id": null,
      "leetcode_url": "https://leetcode.com/problems/meeting-rooms-iii/"
    }
  ]
}
