{
  "category": "",
  "id": "1638",
  "name": "Count Substrings That Differ by One Character",
  "difficulty": "Medium",
  "leetcode_url": "https://leetcode.com/problems/count-substrings-that-differ-by-one-character/",
  "slug": "count-substrings-that-differ-by-one-character",
  "isPaidOnly": false,
  "tags": [
    "Hash Table",
    "String",
    "Dynamic Programming",
    "Enumeration"
  ],
  "similar_questions": [
    {
      "title": "Count Words Obtained After Adding a Letter",
      "slug": "count-words-obtained-after-adding-a-letter",
      "id": null,
      "leetcode_url": "https://leetcode.com/problems/count-words-obtained-after-adding-a-letter/"
    }
  ]
}
