{
  "category": "",
  "id": "2950",
  "name": "Number of Divisible Substrings",
  "difficulty": "Medium",
  "leetcode_url": "https://leetcode.com/problems/number-of-divisible-substrings/",
  "slug": "number-of-divisible-substrings",
  "isPaidOnly": true,
  "tags": [
    "Hash Table",
    "String",
    "Counting",
    "Prefix Sum"
  ],
  "similar_questions": [
    {
      "title": "Count Substrings Divisible By Last Digit",
      "slug": "count-substrings-divisible-by-last-digit",
      "id": null,
      "leetcode_url": "https://leetcode.com/problems/count-substrings-divisible-by-last-digit/"
    }
  ]
}