{
  "category": "",
  "id": "234",
  "name": "Palindrome Linked List",
  "difficulty": "Easy",
  "leetcode_url": "https://leetcode.com/problems/palindrome-linked-list/",
  "slug": "palindrome-linked-list",
  "isPaidOnly": false,
  "tags": [
    "Linked List",
    "Two Pointers",
    "Stack",
    "Recursion"
  ],
  "similar_questions": [
    {
      "title": "Palindrome Number",
      "difficulty": "Easy",
      "slug": "palindrome-number"
    },
    {
      "title": "Valid Palindrome",
      "difficulty": "Easy",
      "slug": "valid-palindrome"
    },
    {
      "title": "Reverse Linked List",
      "difficulty": "Easy",
      "slug": "reverse-linked-list"
    },
    {
      "title": "Maximum Twin Sum of a Linked List",
      "difficulty": "Medium",
      "slug": "maximum-twin-sum-of-a-linked-list"
    }
  ],
  "questionId": "234",
  "questionFrontendId": "234",
  "title": "Palindrome Linked List",
  "titleSlug": "palindrome-linked-list",
  "content": "<p>Given the <code>head</code> of a singly linked list, return <code>true</code><em> if it is a </em><span data-keyword=\"palindrome-sequence\"><em>palindrome</em></span><em> or </em><code>false</code><em> otherwise</em>.</p>\n\n<p>&nbsp;</p>\n<p><strong class=\"example\">Example 1:</strong></p>\n<img alt=\"\" src=\"https://assets.leetcode.com/uploads/2021/03/03/pal1linked-list.jpg\" style=\"width: 422px; height: 62px;\" />\n<pre>\n<strong>Input:</strong> head = [1,2,2,1]\n<strong>Output:</strong> true\n</pre>\n\n<p><strong class=\"example\">Example 2:</strong></p>\n<img alt=\"\" src=\"https://assets.leetcode.com/uploads/2021/03/03/pal2linked-list.jpg\" style=\"width: 182px; height: 62px;\" />\n<pre>\n<strong>Input:</strong> head = [1,2]\n<strong>Output:</strong> false\n</pre>\n\n<p>&nbsp;</p>\n<p><strong>Constraints:</strong></p>\n\n<ul>\n\t<li>The number of nodes in the list is in the range <code>[1, 10<sup>5</sup>]</code>.</li>\n\t<li><code>0 &lt;= Node.val &lt;= 9</code></li>\n</ul>\n\n<p>&nbsp;</p>\n<strong>Follow up:</strong> Could you do it in <code>O(n)</code> time and <code>O(1)</code> space?",
  "likes": 17726,
  "dislikes": 949,
  "stats": {
    "totalAccepted": "2.6M",
    "totalSubmission": "4.6M",
    "totalAcceptedRaw": 2578293,
    "totalSubmissionRaw": 4562931,
    "acRate": "56.5%"
  },
  "topicTags": [
    {
      "name": "Linked List",
      "slug": "linked-list"
    },
    {
      "name": "Two Pointers",
      "slug": "two-pointers"
    },
    {
      "name": "Stack",
      "slug": "stack"
    },
    {
      "name": "Recursion",
      "slug": "recursion"
    }
  ],
  "metaData": {
    "name": "isPalindrome",
    "params": [
      {
        "name": "head",
        "type": "ListNode"
      }
    ],
    "return": {
      "type": "boolean"
    }
  },
  "discussion_posts": [
    {
      "name": "casual-coder",
      "year": 2020,
      "content": "I believe coming up with an O(1) space solution for this problem is not trivial, but do you guys think it can be at medium difficulty?",
      "voteCount": 301
    },
    {
      "name": "tourist_111",
      "year": 2023,
      "content": "This must be a medium question , it\\'s in no way an easy problem.",
      "voteCount": 248
    },
    {
      "name": "aarushidhingra99",
      "year": 2022,
      "content": "Why doesn\\'t simply reversing a linked list and comparing it with the original one work? Only 78/88 cases passed. ",
      "voteCount": 102
    },
    {
      "name": "Sumukha1496",
      "year": 2020,
      "content": "May be I did something extra. But still O(N) time and O(1) space and 1ms solution in java and faster than 95.xx%.\\n1. Find the mid using fast pointer and slow pointer approach = O(N/2) -> O(N).\\n2. Reverse the first half of the list inline = O(N/2) -> O(N) time, O(1) space.\\n3. Compare the 2 lists. = O(N) time, O(1) space.\\n\\nSo overall: O(N) time and O(1) space.",
      "voteCount": 65
    },
    {
      "name": "mstuebs",
      "year": 2024,
      "content": "Make sure to check for these testcases:\\n```\\n[0]\\n[1,6,6,1]\\n[1,1,6,1]\\n[1,6,1,1]\\n[6,1,1,1]\\n[1,1,1,6]\\n[1,6,1,6]\\n[1,6,6,6,1]\\n```",
      "voteCount": 35
    },
    {
      "name": "Chipanzee",
      "year": 2023,
      "content": "I don\\'t understand why the code compiles differently from other compilers.. I have some solution, I run it on other compiler, everything works, and here is not working.. same test case lol",
      "voteCount": 23
    },
    {
      "name": "deleted_user",
      "year": 2023,
      "content": "Great problem, but that\\'s rather a medium problem, isn\\'t it?",
      "voteCount": 18
    },
    {
      "name": "adamstrejcovsky",
      "year": 2023,
      "content": "Is there a constant space solution without messing up the original list? Because after such operation your list will end up changed.",
      "voteCount": 13
    },
    {
      "name": "alitz",
      "year": 2015,
      "content": "It seems the system checks the linked list when judging the answer. If there is a loop in the list, there will be a Time Limit Exceed error.\\n\\nFor example, if you reverse the second half of the list a=>b=>c=>NULL, there will be two result:\\n\\n 1. a-->b--><--c (b's next is c and c's next is b)\\n 2. a-->b-->NULL and c-->b-->NULL (b's next is NULL while a,c's next is b)\\n\\nNote that, the first result does not prevent you from getting a correct result, as long as you record the length of the original list and know where the mid point is, and stop checking at mid point.\\n\\nHowever, the code will have Time Limit Exceed error if you build a list like 1, though your answer is right. This is really misleading.",
      "voteCount": 13
    },
    {
      "name": "user3353xR",
      "year": 2023,
      "content": "A bit confused with this task, what do you actually pass as a parameter while testing in your IDE? The input parameter, head, is a ListNode, the constructor of which is a an integer. In the example use cases the input is an array of integers (obviously meant to represent the entire List) .. So what do you do when you test in your own environment, do you build the LinkedList before the method, and truly pass the head node, or what?",
      "voteCount": 12
    }
  ]
}
